datexplore/__init__.py
datexplore/clean_names.py
datexplore/detect_outliers.py
datexplore/visualise.py
datexplore-0.0.2.dist-info/LICENSE
datexplore-0.0.2.dist-info/METADATA
datexplore-0.0.2.dist-info/WHEEL
datexplore-0.0.2.dist-info/RECORD
