Metadata-Version: 2.1
Name: datexplore
Version: 0.0.2
Summary: A package for exploratory data analysis and data cleaning.
License: MIT
Author: Jordan Cairns, Sid Grover, Scout McKee
Requires-Python: >=3.9.0
Classifier: License :: OSI Approved :: MIT License
Classifier: Programming Language :: Python :: 3
Classifier: Programming Language :: Python :: 3.9
Classifier: Programming Language :: Python :: 3.10
Classifier: Programming Language :: Python :: 3.11
Classifier: Programming Language :: Python :: 3.12
Requires-Dist: pandas (>=2.1.4)
Requires-Dist: seaborn (>=0.11.2,<0.12.0)
